doclib/__init__.py
doclib-1.8.4.data/scripts/__init__.py
doclib-1.8.4.dist-info/LICENSE
doclib-1.8.4.dist-info/METADATA
doclib-1.8.4.dist-info/WHEEL
doclib-1.8.4.dist-info/top_level.txt
doclib-1.8.4.dist-info/RECORD
