Metadata-Version: 2.1
Name: doclib
Version: 1.8.4
Summary: A chatbot library for euphoria.io.
Home-page: https://gitlab.com/DoctorNumberFour/DocLib
Author: DoctorNumberFour
Author-email: miloszecket@gmail.com
License: UNKNOWN
Platform: UNKNOWN
Classifier: Programming Language :: Python :: 3
Classifier: Programming Language :: Python :: 3.8
Classifier: Programming Language :: Python :: 3.7
Classifier: License :: OSI Approved :: GNU General Public License v3 (GPLv3)
Classifier: Operating System :: Unix
Classifier: Operating System :: POSIX
Classifier: Operating System :: Microsoft
Requires-Python: >=3.7
Requires-Dist: websocket-client
Requires-Dist: websockets
Requires-Dist: attrdict
Requires-Dist: colorama
